nexus_agent/__init__.py
nexus_agent/_version.py
nexus_agent/agent.py
nexus_agent/interface.py
nexus_agent/tools/__init__.py
nexus_agent/tools/ai/__init__.py
nexus_agent/tools/ai/image_gen.py
nexus_agent/tools/core/__init__.py
nexus_agent/tools/core/model_selector.py
nexus_agent/tools/dev/__init__.py
nexus_agent/tools/dev/code_interpreter.py
nexus_agent/tools/dev/shell.py
nexus_agent/tools/io/__init__.py
nexus_agent/tools/io/file_operation.py
nexus_agent/tools/io/web_browser.py
nexus_agent/tools/utils/__init__.py
nexus_agent/tools/utils/math_solver.py
nexus_agent/tools/utils/search.py
nexus_agent/tools/utils/time_tools.py
nexus_agent/tools/utils/weather.py
nexus_agent-0.1.0.dist-info/METADATA
nexus_agent-0.1.0.dist-info/WHEEL
nexus_agent-0.1.0.dist-info/top_level.txt
nexus_agent-0.1.0.dist-info/RECORD
