Metadata-Version: 2.1
Name: nexus-agent
Version: 0.1.0
Summary: An AI assistant with advanced tool integration capabilities
Author-email: Andrew Turner <andrewturner28@gmail.com>
License: MIT
Classifier: Development Status :: 3 - Alpha
Classifier: Intended Audience :: Developers
Classifier: License :: OSI Approved :: MIT License
Classifier: Programming Language :: Python :: 3
Classifier: Programming Language :: Python :: 3.11
Requires-Python: >=3.11
Requires-Dist: aiohttp>=3.8.1
Requires-Dist: beautifulsoup4>=4.9.3
Requires-Dist: numpy>=1.19.5
Requires-Dist: openai>=1.0.0
Requires-Dist: Pillow>=8.2.0
Requires-Dist: pydantic>=2.0.0
Requires-Dist: python-dotenv>=0.19.0
Requires-Dist: pytz>=2021.1
Requires-Dist: requests>=2.25.1
Requires-Dist: streamlit>=1.28.0
Requires-Dist: playwright>=1.36.0
